gib_esu/__init__.py
gib_esu/py.typed
gib_esu/helpers/__init__.py
gib_esu/helpers/py_utils.py
gib_esu/models/__init__.py
gib_esu/models/base_model.py
gib_esu/models/request_models.py
gib_esu/models/response_models.py
gib_esu/models/service_models.py
gib_esu/services/__init__.py
gib_esu/services/esu_service.py
gib_esu-1.0.9.dist-info/LICENSE.md
gib_esu-1.0.9.dist-info/METADATA
gib_esu-1.0.9.dist-info/WHEEL
gib_esu-1.0.9.dist-info/top_level.txt
gib_esu-1.0.9.dist-info/RECORD
