Metadata-Version: 2.1
Name: gib-esu
Version: 1.0.9
Summary: GİB EŞÜ EKS servis istemcisi - Electroop
Author-email: Electroop Engineering <dev@electroop.io>
Maintainer-email: Özcan Türkmen <ozcan@electroop.io>
License: # Released under MIT License
Project-URL: homepage, https://github.com/electroop-engineering/gib-esu
Project-URL: repository, https://github.com/electroop-engineering/gib-esu
Project-URL: documentation, https://github.com/electroop-engineering/gib-esu/blob/main/doc.md
Keywords: GİB EŞÜ EKS,Elektrikli şarj üniteleri,şarj ağı işletmecileri
Classifier: Programming Language :: Python :: 3.8
Classifier: Programming Language :: Python :: 3.9
Classifier: Programming Language :: Python :: 3.10
Classifier: Programming Language :: Python :: 3.11
Classifier: Programming Language :: Python :: 3.12
Classifier: Programming Language :: Python :: 3.13
Classifier: License :: OSI Approved :: MIT License
Classifier: Operating System :: OS Independent
Requires-Python: >=3.8
License-File: LICENSE.md
Requires-Dist: requests<3.0.0,>=2.32.3
Requires-Dist: pydantic<3.0.0,>=2.9.2
Requires-Dist: python-dotenv>=1.0.0
Provides-Extra: dev
Requires-Dist: pytest>=8.0.0; extra == "dev"
Requires-Dist: black; extra == "dev"
Requires-Dist: flake8; extra == "dev"
Requires-Dist: mypy; extra == "dev"
Requires-Dist: pre-commit; extra == "dev"
